tuplex.libs/libmagic-a1c7092f.so.1.0.0
tuplex.libs/libcrypto-d3570994.so.1.0.2k
tuplex.libs/libpcre-9513aab5.so.1.2.0
tuplex.libs/libncurses-a6f90868.so.5.9
tuplex.libs/libkrb5support-d0bcff84.so.0.1
tuplex.libs/libk5crypto-b1f99d5c.so.3.1
tuplex.libs/libcurl-52853437.so.4.7.0
tuplex.libs/libform-09052c3b.so.5.9
tuplex.libs/libantlr4-runtime-759a16df.so.4.13.1
tuplex.libs/libcom_err-2abe824b.so.2.1
tuplex.libs/libselinux-0922c95c.so.1
tuplex.libs/libkeyutils-dfe70bd6.so.1.5
tuplex.libs/libtinfo-10270e32.so.5.9
tuplex.libs/libssl-cd1d6220.so.1.0.2k
tuplex.libs/libgssapi_krb5-497db0c6.so.2.2
tuplex.libs/libkrb5-fcafa220.so.3.3
tuplex-0.3.6.dist-info/WHEEL
tuplex-0.3.6.dist-info/top_level.txt
tuplex-0.3.6.dist-info/LICENSE
tuplex-0.3.6.dist-info/RECORD
tuplex-0.3.6.dist-info/METADATA
tuplex/distributed.py
tuplex/__init__.py
tuplex/context.py
tuplex/exceptions.py
tuplex/dataset.py
tuplex/metrics.py
tuplex/utils/errors.py
tuplex/utils/common.py
tuplex/utils/framework.py
tuplex/utils/jupyter.py
tuplex/utils/__init__.py
tuplex/utils/tracebacks.py
tuplex/utils/source_vault.py
tuplex/utils/reflection.py
tuplex/utils/interactive_shell.py
tuplex/utils/globs.py
tuplex/utils/version.py
tuplex/utils/jedi_completer.py
tuplex/historyserver/__init__.py
tuplex/historyserver/run-dev.py
tuplex/historyserver/setup.py
tuplex/historyserver/thserver/common.py
tuplex/historyserver/thserver/__init__.py
tuplex/historyserver/thserver/database.py
tuplex/historyserver/thserver/config.py
tuplex/historyserver/thserver/views.py
tuplex/historyserver/thserver/rest.py
tuplex/historyserver/thserver/version.py
tuplex/historyserver/thserver/templates/job_plan.html
tuplex/historyserver/thserver/templates/overview.html
tuplex/historyserver/thserver/templates/job_config.html
tuplex/historyserver/thserver/templates/job_not_found.html
tuplex/historyserver/thserver/templates/navbar.html
tuplex/historyserver/thserver/templates/job.html
tuplex/historyserver/thserver/static/img/logo.png
tuplex/historyserver/thserver/static/img/favicon.ico
tuplex/historyserver/thserver/static/img/outline.png
