Metadata-Version: 2.1
Name: tuplex
Version: 0.3.6
Summary: Tuplex is a novel big data analytics framework incorporating a Python UDF compiler based on LLVM together with a query compiler featuring whole-stage code generation and optimization.
Home-page: https://tuplex.cs.brown.edu
Author: Leonhard Spiegelberg
Author-email: tuplex@cs.brown.edu
License: Apache 2.0
Project-URL: Bug Tracker, https://github.com/tuplex
Project-URL: Documentation, https://tuplex.cs.brown.edu/python-api.html
Project-URL: Source Code, https://github.com/tuplex
Keywords: ETL BigData Python LLVM UDF Data Analytics
Classifier: Development Status :: 2 - Pre-Alpha
Classifier: Operating System :: MacOS
Classifier: Operating System :: POSIX :: Linux
Classifier: Intended Audience :: Developers
Classifier: License :: OSI Approved :: Apache Software License
Classifier: Programming Language :: Python :: 3.8
Classifier: Programming Language :: Python :: 3.9
Classifier: Programming Language :: Python :: 3.10
Classifier: Programming Language :: Python :: 3.11
Requires-Python: >=3.8.0
License-File: LICENSE
Requires-Dist: Flask <2.2.0,>=2.0.2
Requires-Dist: Werkzeug <2.2.0
Requires-Dist: gunicorn
Requires-Dist: eventlet ==0.30.0
Requires-Dist: flask-socketio
Requires-Dist: flask-pymongo
Requires-Dist: iso8601
Requires-Dist: attrs >=19.2.0
Requires-Dist: dill >=0.2.7.1
Requires-Dist: pluggy
Requires-Dist: py >=1.5.2
Requires-Dist: pygments >=2.4.1
Requires-Dist: six >=1.11.0
Requires-Dist: wcwidth >=0.1.7
Requires-Dist: astor
Requires-Dist: prompt-toolkit
Requires-Dist: jedi
Requires-Dist: PyYAML >=3.13
Requires-Dist: psutil
Requires-Dist: pymongo
Requires-Dist: cloudpickle <2.0.0,>=0.6.1 ; python_version < "3.10"
Requires-Dist: cloudpickle >=2.1.0 ; python_version == "3.10"
Requires-Dist: cloudpickle >=2.2.1 ; python_version >= "3.11"
